{
  "id": "org:ghost-shadows",
  "name": "Ghost Shadows",
  "aliases": [
    "Ghost Shadows Street Gang",
    "GSS"
  ],
  "type": "street_gang",
  "lane": "asian-gangs",
  "founded_year": 1971,
  "founded_year_precision": "exact",
  "description": "The Ghost Shadows was a Chinese American street gang prominent in New York City's Chinatown from the early 1970s to the mid 1990s. Formed in 1971 by immigrants from Taiwan and Hong Kong, it was affiliated with the On Leong Tong. The gang engaged in extortion, kidnapping, murder, racketeering, drug trafficking, and illegal gambling. It became defunct due to federal RICO crackdowns in the 1990s.",
  "sources": [
    {
      "url": "https://en.wikipedia.org/wiki/Ghost_Shadows",
      "title": "Ghost Shadows — Wikipedia"
    },
    {
      "url": "https://en.wikipedia.org/wiki/Born_to_Kill_%28gang%29",
      "title": "Born to Kill %28gang%29 — Wikipedia"
    },
    {
      "url": "https://en.wikipedia.org/wiki/Flying_Dragons_%28gang%29",
      "title": "Flying Dragons %28gang%29 — Wikipedia"
    },
    {
      "url": "https://en.wikipedia.org/wiki/On_Leong_Chinese_Merchants_Association",
      "title": "On Leong Chinese Merchants Association — Wikipedia"
    },
    {
      "url": "https://en.wikipedia.org/wiki/Tiny_Rascal_Gang",
      "title": "Tiny Rascal Gang — Wikipedia"
    }
  ],
  "metro": "New York",
  "status": "inactive",
  "colors": [
    "black"
  ],
  "disbanded_year": 1990
}
